elfinTerminal/scripts/__init__.py
elfinTerminal/scripts/config.py
elfinTerminal/scripts/terminal.py
elfinTerminal/setUp/__init__.py
elfinTerminal/setUp/aptSetUP.py
elfinTerminal/setUp/pipSetUp.py
elfinTerminal/setUp/pypiSetUp.py
elfinTerminal/setUp/vimSetUp.py
elfinTerminal/source/__init__.py
elfinTerminal/source/config.py
elfinTerminal/tools/__init__.py
elfinTerminal/tools/pathSearch.py
elfinterminal-0.0.5.dist-info/licenses/LICENSE
elfinterminal-0.0.5.dist-info/METADATA
elfinterminal-0.0.5.dist-info/WHEEL
elfinterminal-0.0.5.dist-info/entry_points.txt
elfinterminal-0.0.5.dist-info/top_level.txt
elfinterminal-0.0.5.dist-info/RECORD
