Metadata-Version: 2.4
Name: elfinTerminal
Version: 0.0.5
Summary: 终端配置工具.
Classifier: Programming Language :: Python :: 3
Classifier: License :: OSI Approved :: Apache Software License
Requires-Python: >=3.10
License-File: LICENSE
Requires-Dist: prettytable
Requires-Dist: loguru
Dynamic: license-file
